{
  "bookshelf:load_conditions": [
    {
      "type": "bookshelf:item_exists",
      "values": [
        "thermal:corn_seeds",
        "thermal:corn"
      ]
    }
  ],
  "type": "botanypots:crop",
  "seed": {
    "item": "thermal:corn_seeds"
  },
  "categories": [
    "dirt",
    "farmland"
  ],
  "growthTicks": 1200,
  "display": {
    "type": "botanypots:aging",
    "block": "thermal:corn"
  },
  "drops": [
    {
      "chance": 1.00,
      "output": {
        "item": "thermal:corn"
      }
    },
    {
      "chance": 0.05,
      "output": {
        "item": "thermal:corn_seeds"
      }
    }
  ]
}