{
  "bookshelf:load_conditions": [
    {
      "type": "bookshelf:item_exists",
      "values": [
        "betterend:lanceleaf_seed"
      ]
    }
  ],
  "type": "botanypots:crop",
  "seed": {
    "item": "betterend:lanceleaf_seed"
  },
  "categories": [
    "amber_moss"
  ],
  "growthTicks": 1200,
  "display": {
    "type": "botanypots:aging",
    "block": "betterend:lanceleaf_seed"
  },
  "drops": [
    {
      "chance": 1.00,
      "output": {
        "item": "betterend:lanceleaf_seed"
      }
    }
  ]
}