{
	"type":"botanypots:crop",
	"conditions":[
		{
			"type":"forge:mod_loaded",
			"modid":"thermal"
		},
		{
			"type":"thermal:crop_enabled",
			"crop":"thermal:strawberry"
		}
	],
	"seed":{
		"item":"thermal:strawberry_seeds"
	},
	"categories":[
		"dirt"
	],
	"growthTicks":1200,
	"display":{
		"block":"thermal:strawberry",
		"properties":{
			"age":7
		}
	},
	"results":[
		{
			"chance":0.75,
			"output":{
				"item":"thermal:strawberry"
			},
			"minRolls":1,
			"maxRolls":1
		},
		{
			"chance":0.05,
			"output":{
				"item":"thermal:strawberry_seeds"
			},
			"minRolls":1,
			"maxRolls":1
		}
	]
}